telepack/__init__.py
telepack/endpoints.py
telepack/metric.py
telepack/trace.py
telepack-0.0.3.dist-info/LICENSE
telepack-0.0.3.dist-info/METADATA
telepack-0.0.3.dist-info/WHEEL
telepack-0.0.3.dist-info/top_level.txt
telepack-0.0.3.dist-info/RECORD
