Metadata-Version: 2.2
Name: telepack
Version: 0.0.3
Summary: Add observability to your project or Jupyter Notebook. Even more easily surface telemetry stats to New Relic
Author-email: "David Bower, Koales Ltd." <open-source@koales.co.uk>
Project-URL: Homepage, https://github.com/koales/telepack
Project-URL: Issues, https://github.com/koales/telepack/issues
Keywords: observability,telemetry,timing,trace,span,new relic,jupyter
Classifier: Development Status :: 3 - Alpha
Classifier: Topic :: System :: Monitoring
Classifier: Programming Language :: Python :: Implementation :: PyPy
Classifier: Programming Language :: Python :: Implementation :: CPython
Classifier: Programming Language :: Python :: 3
Classifier: Programming Language :: Python :: 3.7
Classifier: Programming Language :: Python :: 3.8
Classifier: Programming Language :: Python :: 3.9
Classifier: Programming Language :: Python :: 3.10
Classifier: Programming Language :: Python :: 3.11
Classifier: Programming Language :: Python :: 3.12
Classifier: Operating System :: OS Independent
Classifier: License :: OSI Approved :: Apache Software License
Requires-Python: >=3.7
License-File: LICENSE
Requires-Dist: newrelic-telemetry-sdk>=0.6.0
